easel/__init__.py
easel/__main__.py
easel/assignment.py
easel/assignment_group.py
easel/canvas_id.py
easel/commands.py
easel/component.py
easel/course.py
easel/external_tool.py
easel/files.py
easel/grading_scheme.py
easel/helpers.py
easel/helpers_yaml.py
easel/module.py
easel/module_item.py
easel/navigation_tab.py
easel/page.py
easel/quiz.py
easel/quiz_question.py
easel_cli-1.1.1.dist-info/LICENSE
easel_cli-1.1.1.dist-info/METADATA
easel_cli-1.1.1.dist-info/WHEEL
easel_cli-1.1.1.dist-info/entry_points.txt
easel_cli-1.1.1.dist-info/top_level.txt
easel_cli-1.1.1.dist-info/RECORD
