Metadata-Version: 2.1
Name: easel-cli
Version: 1.1.1
Summary: A Canvas course management tool
Home-page: https://github.com/renquinn/easel-py
Author: Ren Quinn
Author-email: renquinn@gmail.com
Classifier: Programming Language :: Python :: 3
Classifier: License :: OSI Approved :: GNU General Public License v3 (GPLv3)
Classifier: Operating System :: OS Independent
Requires-Python: >=3.7
License-File: LICENSE
Requires-Dist: markdown ==3.3.4
Requires-Dist: pygments ==2.11.2
Requires-Dist: pyyaml
Requires-Dist: requests
Requires-Dist: tinydb
Requires-Dist: tqdm
